src/main.py
python_action-0.1.4.dist-info/METADATA
python_action-0.1.4.dist-info/WHEEL
python_action-0.1.4.dist-info/RECORD
